benchmark/plotting/benchmark_plot.py
benchmark/plotting/plot.py
benchmark/plotting/plot_utils.py
ip6_access_control-1.0.0.post5.dist-info/licenses/LICENCE
shared/conf_utils.py
shared/logging_config.py
supervisor/supervisor.py
user_tool/default.json
user_tool/group_selector.py
user_tool/groups
user_tool/policy_manager.py
user_tool/user_interaction.py
user_tool/user_tool_main.py
ip6_access_control-1.0.0.post5.dist-info/METADATA
ip6_access_control-1.0.0.post5.dist-info/WHEEL
ip6_access_control-1.0.0.post5.dist-info/entry_points.txt
ip6_access_control-1.0.0.post5.dist-info/top_level.txt
ip6_access_control-1.0.0.post5.dist-info/RECORD
