Metadata-Version: 2.4
Name: ip6-access-control
Version: 1.0.0.post5
Summary: A project with a supervisor and a central daemon.
Author: Damjan Mlinar, Viktor Weilenmann
License-Expression: GPL-3.0-or-later
Project-URL: Homepage, https://github.com/Soldatstar/ip6-access-control
Project-URL: Issues, https://github.com/Soldatstar/ip6-access-control/issues
Classifier: Programming Language :: Python :: 3
Classifier: Operating System :: POSIX :: Linux
Requires-Python: >=3.9
License-File: LICENCE
Requires-Dist: python-ptrace==0.9.9
Requires-Dist: pyseccomp==0.1.2
Requires-Dist: pyzmq==26.4.0
Provides-Extra: dev
Requires-Dist: pytest==8.3.5; extra == "dev"
Requires-Dist: pytest-mock==3.14.0; extra == "dev"
Requires-Dist: coverage==7.8.0; extra == "dev"
Requires-Dist: pylint==3.3.7; extra == "dev"
Requires-Dist: build==1.2.2.post1; extra == "dev"
Dynamic: license-file
